nkotranslit/__init__.py
nkotranslit/cli.py
nkotranslit/convert.py
nkotranslit/gui.py
nkotranslit-1.1.1.dist-info/METADATA
nkotranslit-1.1.1.dist-info/WHEEL
nkotranslit-1.1.1.dist-info/entry_points.txt
nkotranslit-1.1.1.dist-info/top_level.txt
nkotranslit-1.1.1.dist-info/RECORD
